source/cpuController.v
module  cpuController( // CPU control unit (FMA)
    input wire clk, // Clock
    input wire rst, // Reset
    input wire[15:0] opcode, // Current instruction

    output reg[1:0] memAddr, // Source of memory address
    output reg enPC, // Enable write to program counter
    output reg saveOpcode, // Enable write to instruction register
    output reg saveMem, // Enable write to internal value register
    output reg[3:0] aluFunc, // ALU control bus
    output reg[2:0] aluA, // Source of ALU input A
    output reg[2:0] aluB, // Source of ALU input B
    output reg enA, // Enable write to A register
    output reg enB, // Enable write to B register
    output reg enC  // Enable write to C register
    );

`include "../source/constants"

parameter [4:0] FETCH = 5'b00000; // Instruction fetching cycle
parameter [4:0] ATYPE = 5'b00001; // Execution of A Type instructions
parameter [4:0] ITYPE = 5'b00010; // Execution of I Type instructions
parameter [4:0] HALT = 5'b11111; // CPU stop

parameter [4:0] RIMMED = 5'b10000; // Read immediate value


reg[4:0] state; // Current FSM state
reg[4:0] nextState; // Next FSM state

reg[4:0] returnState; // State to which FSM will return after reading value

wire[2:0] s1 = opcode[11:9]; // Source 1 field of opcode (common for all)

always @ (posedge clk or posedge rst) begin // FMS sequential logic
    if (rst) begin // Reset of all state registes
        state <= FETCH;
        returnState <= FETCH;
    end else begin
        state <= nextState; // Go to next state
    end
end

always @ (*) begin
    nextState = HALT; // If invalid state, then stop CPU
    case (state)
        FETCH: begin
            if (s1[2] == 1'b0) // If read addressing mode == register
                nextState = returnState; // To main state of instruction type
            else if (s1 == 3'b100) // If read addressing mode == immediate
                nextState = RIMMED;
        end
        ATYPE: nextState = FETCH; // Fetch next instruction
        ITYPE: nextState = FETCH; // Fetch next instruction
        RIMMED: nextState = returnState; // To main state of instruction type
    endcase

    returnState = HALT; // If invalid instruction, then stop CPU

    if (opcode[15:12] == 4'b0000) // A Type
        returnState = ATYPE;
    else if (opcode[15:14] == 2'b01) // I Type
        returnState = ITYPE;
end

always @ (*) begin
    memAddr = 0; // If not important, set everything to 0
    enPC = 0;
    saveOpcode = 0;
    aluFunc = 0;
    aluA = 0;
    aluB = 0;
    enA = 0;
    enB = 0;
    enC = 0;
    saveMem = 0;
    case (state)
        FETCH: begin
            memAddr = READ_FROM_PC; // Fetch instruction
            saveOpcode = 1;

            aluFunc = 4'b0000; // Increment PC
            aluA = ALU1_FROM_PC;
            aluB = ALU2_FROM_1;
            enPC = 1;
        end

        ATYPE: begin

            if (s1[2] == 1'b0) // If reading from register
                aluA = s1[1:0];
            else // If reading from memory
                aluA = ALU1_FROM_MEM;
            aluB = opcode[4:3]; // Source for ALU input B
            aluFunc = opcode[8:5]; // ALU control is in the instruction
            case (opcode[1:0]) // Destination
                DEST_A: enA = 1;
                DEST_B: enB = 1;
                DEST_C: enC = 1;
            endcase
        end

        ITYPE: begin
            if (s1[2] == 1'b0) // If reading from register
                aluA = s1[1:0];
            else // If reading from memory
                aluA = ALU1_FROM_MEM;
            // ALU control is in pattern 3312 if opcode - 12|3
            aluFunc = {opcode[8], opcode[8], opcode[13:12]};
            aluB = ALU2_FROM_OP; // Source for ALU input B
            case (s1) // Destination
                DEST_A: enA = 1;
                DEST_B: enB = 1;
                DEST_C: enC = 1;
            endcase
        end

        RIMMED: begin // Read immediate value
            memAddr = READ_FROM_PC; // Read value from (PC)
            saveMem = 1;

            aluFunc = 4'b0000; // Increment PC
            aluA = ALU1_FROM_PC;
            aluB = ALU2_FROM_1;
            enPC = 1;
        end
    endcase
end
endmodule

source/alu.v
module alu(
    input wire[N-1:0] a,
    input wire[N-1:0] b,
    input wire[3:0] func,
    input wire ci,
    output reg[N-1:0] y,
    output reg[N-1:0] outToA,
    output reg co,
    output reg zero,
    output reg overflow,
    output reg negative );

parameter N = 16;



reg[N-1:0] negatedB;
reg[N:0] negatedCI;

reg[N-1:0] rshift;
reg[N-1:0] rrotate;
reg[N-1:0] lrotate;
reg[N-1:0] lshift;

wire[2*N-1:0] mul = {{N{a[N-1]}}, a} * {{N{b[N-1]}}, b};

reg invCO;
reg signed[N:0] sigA;

always @ (a, b, ci, func) begin
    y = 0;
    co  = 0;
    outToA = 0;
    overflow = 0;

    negatedB = func[1] ? -b : b;
    negatedCI = func[1] ? -ci : ci;
    sigA = {a, 1'b0};
    {rshift, rrotate} = {a, a} >> b[3:0];
    {lrotate, lshift} = ({a, a} << b[3:0]);

    casez (func)
        4'b00zz: begin
            {invCO, y} = a + negatedB + (func[0] ? negatedCI : 16'b0);
            overflow = (a[N-1] == negatedB[N-1]) & (y[N-1] != a[N-1]);
            co = func[1] ^ invCO;
        end
        4'b01zz: begin
            if (func[1:0] != 2'b11) begin
                {outToA, y} = {{N{a[N-1]}}, a} * {{N{b[N-1]}}, b};
                overflow = (outToA != 0 && outToA != 16'hFFFF) && func[0];
            end else begin
                {y, co} = sigA >>> b[3:0];
            end
        end
        4'b1000: {co, y} = {lrotate[0], lshift};
        4'b1001: {co, y} = {rrotate[N-1], rshift};
        4'b1010: y = lrotate;
        4'b1011: y = rrotate;
        4'b1100: y = a & b;
        4'b1101: y = a | b;
        4'b1110: y = a ^ b;
        4'b1111: y = ~a;
    endcase

    zero = y == 0 && outToA == 0;
    negative = outToA == 0? y[N-1] : outToA[N-1];
end

endmodule

source/register.v
module register( // Register
    input wire clk, // Clock
    input wire[N-1:0] in, // Data to write
    output reg[N-1:0] out, // Data from register
    input wire en, // Write enable
    input wire rst); // Reset

parameter N = 16; // Width

always @ (posedge clk or posedge rst)
    if (rst) // Set to 0 at reset
        out <= 0;
    else if (en) // Write to register
        out <= in;

endmodule

source/rcpu.v
`include "../source/register.v"
`include "../source/alu.v"
`include "../source/cpuController.v"

module rcpu ( // RCPU
    input rst, // Reset
    input clk, // Clock
    output[M-1:0] memAddr, // Memory address
    input[M-1:0] memRead, // Readed from memory
    output[M-1:0] memWrite, // For writing to memory
    output memWE); // Enable writing to memory

`include "../source/constants"

parameter M = 16; // Bus width

wire[M-1:0] A; // A register
wire[M-1:0] B; // B register
wire[M-1:0] C; // C register
wire[M-1:0] PC; // Program counter
wire enA; // Enable write to A
wire enB; // Enable write to B
wire enC; // Enable write to C
wire[M-1:0] inR = aluY; // Input to ABC registers
wire[M-1:0] inPC = aluY; // Input to program counter
wire enPC; // Enable write to

wire[M-1:0] opcode; // Output of instruction register
wire enIR; // Enable write to instruction register
wire[M-1:0] value; // Output of internal value register
wire enV; // Enable write to internal value register

wire[3:0] F; // Output of flag register
wire enF; // Enable write to flag register
wire[3:0] inF; // Input to flag register

wire c = F[3]; // Carry flag
wire n = F[2]; // Negative flag
wire z = F[1]; // Zero flag
wire v = F[0]; // Overflow flag

register #(M) rIR (clk, memRead, opcode, enIR, rst); // Instruction register
register #(M) rV (clk, memRead, value, enV, rst); // Internal value register

register #(M) rA  (clk, inR,  A,  enA,  rst); // A register
register #(M) rB  (clk, inR,  B,  enB,  rst); // B register
register #(M) rC  (clk, inR,  C,  enC,  rst); // C register
register #(M) rPC (clk, inPC, PC, enPC, rst); // Program counter
register #(4) rF  (clk, inF,  F,  enF,  rst); // Flag register

reg[M-1:0] aluA; // ALU input A
reg[M-1:0] aluB; // ALU input B
wire[M-1:0] aluY; // ALU output Y
wire[3:0] aluFunc; // ALU function control bus
wire[M-1:0] aluOutA; // ALU output to A register

wire[2:0] aluASource; // Source of ALU input A
wire[2:0] aluBSource; // Source of ALU input B

alu alu1 ( // ALU
    .a (aluA), // ALU input A
    .b (aluB), // ALU input B
    .y (aluY), // ALU output Y
    .func (aluFunc), // ALU control bus

    .co (inF[3]), // Carry flag out
    .negative (inF[2]), // Negative flag
    .zero (inF[1]), // Zero flag
    .overflow (inF[0]), // Overflow flag

    .ci (c), // Carry flag in
    .outToA (aluOutA) // ALU output to A register
    );



cpuController cpuCTRL ( // CPU control unit (FSM)
    .clk (clk), // Clock
    .rst (rst), // Reset
    .opcode (enIR? memRead : opcode), // Current instruction
    .enPC (enPC), // Out: Enable write to program counter
    .aluFunc (aluFunc), // Out: ALU control bus
    .aluA (aluASource), // Out: Source of ALU input A
    .aluB (aluBSource), // Out: Source of ALU input B
    .enA (enA), // Out: Enable write to A register
    .enB (enB), // Out: Enable write to B register
    .enC (enC), // Out: Enable write to C register
    .saveOpcode (enIR), // Out: Enable write to instruction register
    .saveMem (enV) // Out: Enable write to internal value register
    );

always @ ( * ) begin // ALU input A logic
    aluA = 0; // If none, equals 0
    case (aluASource)
        ALU1_FROM_0: aluA = 0;
        ALU1_FROM_A: aluA = A;
        ALU1_FROM_B: aluA = B;
        ALU1_FROM_C: aluA = C;
        ALU1_FROM_PC: aluA = PC;
        ALU1_FROM_MEM: aluA = value;
    endcase
end

always @ ( * ) begin // ALU input B logic
    aluB = 0; // If none, equals 0
    case (aluBSource)
        ALU2_FROM_0: aluB = 0;
        ALU2_FROM_A: aluB = A;
        ALU2_FROM_B: aluB = B;
        ALU2_FROM_C: aluB = C;
        ALU2_FROM_OP: aluB = opcode[7:0]; // From instruction itself
        ALU2_FROM_1: aluB = 1;
    endcase
end

assign memAddr = PC; // Temporal

endmodule

source/RAM.v
module RAM ( // Random Access Memory Emulation
    input wire rst, // Reset
    input wire clk, // Clock
    input wire[addrSize-1:0] addr, // Address
    input wire[wordSize-1:0] wdata, // Data for writing
    input wire we, // Write enable
    output wire[wordSize-1:0] rdata); // Asynchronous read

parameter addrSize = 16; // Address bus width
parameter wordSize = 16; // Data bus width
parameter depth = 1 << addrSize;



reg[wordSize-1:0] memory[0:depth-1]; // Main memory

assign rdata = memory[addr];  // Asynchronous read

integer i;

always @ (posedge clk or posedge rst)
    if (rst) // Set every cell to 0
        for (i = 0; i < depth; i++)
            memory[i] <= 0;
    else if (we) // Set cell memory[addr] to wdata
        memory[addr] <= wdata;
endmodule

testbenches/testRCPU.v
`include "../source/rcpu.v"
`include "../source/RAM.v"

module testRCPU;
    reg clk;
    reg rst;

    wire[15:0] addr;
    wire[15:0] read;

    RAM ram(
        .clk (clk),
        .rst (rst),
        .addr (addr),
        .rdata (read)
        );

    rcpu cpu(
        .clk (clk),
        .rst (rst),
        .memAddr (addr),
        .memRead (read)
        );

    initial begin
        $dumpfile ("../test.vcd");
        $dumpvars;
    end

    always #5 clk = !clk;

    initial begin
        clk = 0;
        rst = 1;
        #1 rst = 0; $readmemh("../cputest.mif", ram.memory); #9
        #200 $finish;
    end

endmodule

test.vcd
$date
	Sat Mar  4 18:34:49 2017
$end
$version
	Icarus Verilog
$end
$timescale
	1s
$end
$scope module testRCPU $end
$var wire 16 ! read [15:0] $end
$var wire 16 " addr [15:0] $end
$var reg 1 # clk $end
$var reg 1 $ rst $end
$scope module cpu $end
$var wire 1 # clk $end
$var wire 1 % enF $end
$var wire 16 & inPC [15:0] $end
$var wire 16 ' inR [15:0] $end
$var wire 16 ( memAddr [15:0] $end
$var wire 1 ) memWE $end
$var wire 16 * memWrite [15:0] $end
$var wire 1 $ rst $end
$var wire 1 + z $end
$var wire 16 , value [15:0] $end
$var wire 1 - v $end
$var wire 16 . opcode [15:0] $end
$var wire 1 / n $end
$var wire 16 0 memRead [15:0] $end
$var wire 4 1 inF [3:0] $end
$var wire 1 2 enV $end
$var wire 1 3 enPC $end
$var wire 1 4 enIR $end
$var wire 1 5 enC $end
$var wire 1 6 enB $end
$var wire 1 7 enA $end
$var wire 1 8 c $end
$var wire 16 9 aluY [15:0] $end
$var wire 16 : aluOutA [15:0] $end
$var wire 4 ; aluFunc [3:0] $end
$var wire 3 < aluBSource [2:0] $end
$var wire 3 = aluASource [2:0] $end
$var wire 16 > PC [15:0] $end
$var wire 4 ? F [3:0] $end
$var wire 16 @ C [15:0] $end
$var wire 16 A B [15:0] $end
$var wire 16 B A [15:0] $end
$var reg 16 C aluA [15:0] $end
$var reg 16 D aluB [15:0] $end
$scope module alu1 $end
$var wire 16 E a [15:0] $end
$var wire 16 F b [15:0] $end
$var wire 1 8 ci $end
$var wire 32 G mul [31:0] $end
$var wire 4 H func [3:0] $end
$var reg 1 I co $end
$var reg 1 J invCO $end
$var reg 16 K lrotate [15:0] $end
$var reg 16 L lshift [15:0] $end
$var reg 16 M negatedB [15:0] $end
$var reg 17 N negatedCI [16:0] $end
$var reg 1 O negative $end
$var reg 16 P outToA [15:0] $end
$var reg 1 Q overflow $end
$var reg 16 R rrotate [15:0] $end
$var reg 16 S rshift [15:0] $end
$var reg 17 T sigA [16:0] $end
$var reg 16 U y [15:0] $end
$var reg 1 V zero $end
$upscope $end
$scope module cpuCTRL $end
$var wire 1 # clk $end
$var wire 16 W opcode [15:0] $end
$var wire 1 $ rst $end
$var wire 3 X s1 [2:0] $end
$var reg 3 Y aluA [2:0] $end
$var reg 3 Z aluB [2:0] $end
$var reg 4 [ aluFunc [3:0] $end
$var reg 1 7 enA $end
$var reg 1 6 enB $end
$var reg 1 5 enC $end
$var reg 1 3 enPC $end
$var reg 2 \ memAddr [1:0] $end
$var reg 5 ] nextState [4:0] $end
$var reg 5 ^ returnState [4:0] $end
$var reg 1 2 saveMem $end
$var reg 1 4 saveOpcode $end
$var reg 5 _ state [4:0] $end
$upscope $end
$scope module rA $end
$var wire 1 # clk $end
$var wire 1 7 en $end
$var wire 16 ` in [15:0] $end
$var wire 1 $ rst $end
$var reg 16 a out [15:0] $end
$upscope $end
$scope module rB $end
$var wire 1 # clk $end
$var wire 1 6 en $end
$var wire 16 b in [15:0] $end
$var wire 1 $ rst $end
$var reg 16 c out [15:0] $end
$upscope $end
$scope module rC $end
$var wire 1 # clk $end
$var wire 1 5 en $end
$var wire 16 d in [15:0] $end
$var wire 1 $ rst $end
$var reg 16 e out [15:0] $end
$upscope $end
$scope module rF $end
$var wire 1 # clk $end
$var wire 1 % en $end
$var wire 4 f in [3:0] $end
$var wire 1 $ rst $end
$var reg 4 g out [3:0] $end
$upscope $end
$scope module rIR $end
$var wire 1 # clk $end
$var wire 1 4 en $end
$var wire 1 $ rst $end
$var wire 16 h in [15:0] $end
$var reg 16 i out [15:0] $end
$upscope $end
$scope module rPC $end
$var wire 1 # clk $end
$var wire 1 3 en $end
$var wire 16 j in [15:0] $end
$var wire 1 $ rst $end
$var reg 16 k out [15:0] $end
$upscope $end
$scope module rV $end
$var wire 1 # clk $end
$var wire 1 2 en $end
$var wire 1 $ rst $end
$var wire 16 l in [15:0] $end
$var reg 16 m out [15:0] $end
$upscope $end
$upscope $end
$scope module ram $end
$var wire 16 n addr [15:0] $end
$var wire 1 # clk $end
$var wire 16 o rdata [15:0] $end
$var wire 1 $ rst $end
$var wire 16 p wdata [15:0] $end
$var wire 1 q we $end
$var integer 32 r i [31:0] $end
$upscope $end
$upscope $end
$enddefinitions $end
#0
$dumpvars
b10000000000000000 r
zq
bz p
b0 o
b0 n
b0 m
b0 l
b0 k
b1 j
b0 i
b0 h
b0 g
b0 f
b0 e
b1 d
b0 c
b1 b
b0 a
b1 `
b0 _
b1 ^
b0 ]
b0 \
b0 [
b111 Z
b100 Y
b0 X
b0 W
0V
b1 U
b0 T
b0 S
b0 R
0Q
b0 P
0O
b0 N
b1 M
b0 L
b0 K
0J
0I
b0 H
b0 G
b1 F
b0 E
b1 D
b0 C
b0 B
b0 A
b0 @
b0 ?
b0 >
b100 =
b111 <
b0 ;
b0 :
b1 9
08
07
06
05
14
13
02
b0 1
b0 0
0/
b0 .
0-
b0 ,
0+
bz *
z)
b0 (
b1 '
b1 &
z%
1$
0#
b0 "
b0 !
$end
#1
b1 &
b1 j
b1 '
b1 `
b1 b
b1 d
b1 9
b1 U
b1 D
b1 F
b111 <
b111 Z
b100 =
b100 Y
14
13
b1 ^
b10000 ]
b100 X
b100000001001 W
b100000001001 !
b100000001001 0
b100000001001 h
b100000001001 l
b100000001001 o
0$
#5
b100 X
b10 K
b10 L
b1000000000000000 R
b10 T
b10 &
b10 j
b10 '
b10 `
b10 b
b10 d
b10 9
b10 U
12
b111 <
b111 Z
b100 =
b100 Y
04
13
b1 ^
b1 ]
b1 G
b1 C
b1 E
b100000001001 W
b1 D
b1 F
b10000 _
b10 !
b10 0
b10 h
b10 l
b10 o
b1 "
b1 (
b1 n
b1 >
b1 k
b100000001001 .
b100000001001 i
1#
#10
0#
#15
b10 S
b10 R
b100 T
b0 M
b10 &
b10 j
b10 '
b10 `
b10 b
b10 d
b10 9
b10 U
b0 D
b0 F
b0 G
b10 C
b10 E
17
02
b1 <
b1 Z
b101 =
b101 Y
03
b1 ^
b0 ]
b10 ,
b10 m
b100010001001 !
b100010001001 0
b100010001001 h
b100010001001 l
b100010001001 o
b10 "
b10 (
b10 n
b10 >
b10 k
b1 _
1#
#20
0#
#25
b100010001001 W
b100 K
b100 L
b1 S
b1 R
b1 M
b11 &
b11 j
b11 '
b11 `
b11 b
b11 d
b11 9
b11 U
13
14
07
b111 <
b111 Z
b100 =
b100 Y
b1 ^
b10000 ]
b10 C
b10 E
b10 G
b1 D
b1 F
b0 _
b10 B
b10 a
1#
#30
0#
#35
b110 K
b110 L
b1000000000000001 R
b110 T
b100 &
b100 j
b100 '
b100 `
b100 b
b100 d
b100 9
b100 U
b1 D
b1 F
b11 G
b11 C
b11 E
12
b111 <
b111 Z
b100 =
b100 Y
04
13
b1 ^
b1 ]
b100010001001 .
b100010001001 i
b10 !
b10 0
b10 h
b10 l
b10 o
b11 "
b11 (
b11 n
b11 >
b11 k
b10000 _
1#
#40
0#
#45
b10 M
b10 D
b10 F
b1000 K
b1000 L
b0 S
b1000000000000000 R
b100 T
b100 &
b100 j
b100 '
b100 `
b100 b
b100 d
b100 9
b100 U
17
b100 ;
b100 H
b100 [
02
b1 <
b1 Z
b101 =
b101 Y
03
b1 ^
b0 ]
b100 G
b10 C
b10 E
b1 _
b0 !
b0 0
b0 h
b0 l
b0 o
b100 "
b100 (
b100 n
b100 >
b100 k
1#
#50
0#
#55
b0 X
b0 W
b10 S
b10 R
b1000 T
b1 M
b101 &
b101 j
b101 '
b101 `
b101 b
b101 d
b101 9
b101 U
b100 C
b100 E
b100 G
b1 D
b1 F
13
14
07
b111 <
b111 Z
b100 =
b100 Y
b0 ;
b0 H
b0 [
b1 ^
b1 ]
b100 B
b100 a
b0 _
1#
#60
0#
#65
b10 1
b10 f
1V
b0 S
b0 M
b0 K
b0 L
b0 R
b0 T
b0 &
b0 j
b0 '
b0 `
b0 b
b0 d
b0 9
b0 U
b0 <
b0 Z
b0 =
b0 Y
04
03
b1 ^
b0 ]
b0 C
b0 E
b0 G
b0 D
b0 F
b1 _
b101 "
b101 (
b101 n
b101 >
b101 k
b0 .
b0 i
1#
#70
0#
#75
b0 1
b0 f
0V
b110 &
b110 j
b110 '
b110 `
b110 b
b110 d
b110 9
b110 U
b1010 K
b1010 L
b10 S
b1000000000000010 R
b1010 T
b1 M
b101 G
b1 D
b1 F
b101 C
b101 E
13
b111 <
b111 Z
b100 =
b100 Y
14
b1 ^
b1 ]
b0 _
1#
#80
0#
#85
b10 1
b10 f
1V
b0 M
b0 D
b0 F
b0 K
b0 L
b0 S
b0 R
b0 T
b0 &
b0 j
b0 '
b0 `
b0 b
b0 d
b0 9
b0 U
b0 <
b0 Z
b0 =
b0 Y
04
03
b1 ^
b0 ]
b0 G
b0 C
b0 E
b1 _
b110 "
b110 (
b110 n
b110 >
b110 k
1#
#90
0#
#95
b0 1
b0 f
0V
b111 &
b111 j
b111 '
b111 `
b111 b
b111 d
b111 9
b111 U
b1100 K
b1100 L
b11 S
b11 R
b1100 T
b1 M
b110 G
b1 D
b1 F
b110 C
b110 E
13
b111 <
b111 Z
b100 =
b100 Y
14
b1 ^
b1 ]
b0 _
1#
#100
0#
#105
b10 1
b10 f
1V
b0 S
b0 M
b0 D
b0 F
b0 K
b0 L
b0 R
b0 T
b0 &
b0 j
b0 '
b0 `
b0 b
b0 d
b0 9
b0 U
b0 <
b0 Z
b0 =
b0 Y
04
03
b1 ^
b0 ]
b0 G
b0 C
b0 E
b1 _
b111 "
b111 (
b111 n
b111 >
b111 k
1#
#110
0#
#115
b0 1
b0 f
0V
b1000 &
b1000 j
b1000 '
b1000 `
b1000 b
b1000 d
b1000 9
b1000 U
b1110 K
b1110 L
b11 S
b1000000000000011 R
b1110 T
b1 M
b111 G
b1 D
b1 F
b111 C
b111 E
13
b111 <
b111 Z
b100 =
b100 Y
14
b1 ^
b1 ]
b0 _
1#
#120
0#
#125
b10 1
b10 f
1V
b0 M
b0 D
b0 F
b0 K
b0 L
b0 S
b0 R
b0 T
b0 &
b0 j
b0 '
b0 `
b0 b
b0 d
b0 9
b0 U
b0 <
b0 Z
b0 =
b0 Y
04
03
b1 ^
b0 ]
b0 G
b0 C
b0 E
b1 _
b1000 "
b1000 (
b1000 n
b1000 >
b1000 k
1#
#130
0#
#135
b0 1
b0 f
0V
b1001 &
b1001 j
b1001 '
b1001 `
b1001 b
b1001 d
b1001 9
b1001 U
b10000 K
b10000 L
b100 S
b100 R
b10000 T
b1 M
b1000 G
b1 D
b1 F
b1000 C
b1000 E
13
b111 <
b111 Z
b100 =
b100 Y
14
b1 ^
b1 ]
b0 _
1#
#140
0#
#145
b10 1
b10 f
1V
b0 S
b0 M
b0 D
b0 F
b0 K
b0 L
b0 R
b0 T
b0 &
b0 j
b0 '
b0 `
b0 b
b0 d
b0 9
b0 U
b0 <
b0 Z
b0 =
b0 Y
04
03
b1 ^
b0 ]
b0 G
b0 C
b0 E
b1 _
b1001 "
b1001 (
b1001 n
b1001 >
b1001 k
1#
#150
0#
#155
b0 1
b0 f
0V
b1010 &
b1010 j
b1010 '
b1010 `
b1010 b
b1010 d
b1010 9
b1010 U
b10010 K
b10010 L
b100 S
b1000000000000100 R
b10010 T
b1 M
b1001 G
b1 D
b1 F
b1001 C
b1001 E
13
b111 <
b111 Z
b100 =
b100 Y
14
b1 ^
b1 ]
b0 _
1#
#160
0#
#165
b10 1
b10 f
1V
b0 M
b0 D
b0 F
b0 K
b0 L
b0 S
b0 R
b0 T
b0 &
b0 j
b0 '
b0 `
b0 b
b0 d
b0 9
b0 U
b0 <
b0 Z
b0 =
b0 Y
04
03
b1 ^
b0 ]
b0 G
b0 C
b0 E
b1 _
b1010 "
b1010 (
b1010 n
b1010 >
b1010 k
1#
#170
0#
#175
b0 1
b0 f
0V
b1011 &
b1011 j
b1011 '
b1011 `
b1011 b
b1011 d
b1011 9
b1011 U
b10100 K
b10100 L
b101 S
b101 R
b10100 T
b1 M
b1010 G
b1 D
b1 F
b1010 C
b1010 E
13
b111 <
b111 Z
b100 =
b100 Y
14
b1 ^
b1 ]
b0 _
1#
#180
0#
#185
b10 1
b10 f
1V
b0 S
b0 M
b0 D
b0 F
b0 K
b0 L
b0 R
b0 T
b0 &
b0 j
b0 '
b0 `
b0 b
b0 d
b0 9
b0 U
b0 <
b0 Z
b0 =
b0 Y
04
03
b1 ^
b0 ]
b0 G
b0 C
b0 E
b1 _
b1011 "
b1011 (
b1011 n
b1011 >
b1011 k
1#
#190
0#
#195
b0 1
b0 f
0V
b1100 &
b1100 j
b1100 '
b1100 `
b1100 b
b1100 d
b1100 9
b1100 U
b10110 K
b10110 L
b101 S
b1000000000000101 R
b10110 T
b1 M
b1011 G
b1 D
b1 F
b1011 C
b1011 E
13
b111 <
b111 Z
b100 =
b100 Y
14
b1 ^
b1 ]
b0 _
1#
#200
0#
#205
b10 1
b10 f
1V
b0 M
b0 D
b0 F
b0 K
b0 L
b0 S
b0 R
b0 T
b0 &
b0 j
b0 '
b0 `
b0 b
b0 d
b0 9
b0 U
b0 <
b0 Z
b0 =
b0 Y
04
03
b1 ^
b0 ]
b0 G
b0 C
b0 E
b1 _
b1100 "
b1100 (
b1100 n
b1100 >
b1100 k
1#
